agstoolbox/__init__.py
agstoolbox/__main__.py
agstoolbox/at_fonts.py
agstoolbox/at_icons.py
agstoolbox/at_tasks.py
agstoolbox/at_trayindicator.py
agstoolbox/getdata.py
agstoolbox/core/__init__.py
agstoolbox/core/ags/__init__.py
agstoolbox/core/ags/ags_editor.py
agstoolbox/core/ags/ags_editor_validation_data.py
agstoolbox/core/ags/ags_editor_versions.py
agstoolbox/core/ags/ags_export.py
agstoolbox/core/ags/ags_local_run.py
agstoolbox/core/ags/ags_template.py
agstoolbox/core/ags/datafile_writer.py
agstoolbox/core/ags/game_project.py
agstoolbox/core/ags/game_project_compiled.py
agstoolbox/core/ags/get_game_projects.py
agstoolbox/core/ags/get_local_ags_editors.py
agstoolbox/core/ags/get_script_module.py
agstoolbox/core/ags/multifile.py
agstoolbox/core/ags/multifilelib.py
agstoolbox/core/ags/package_compiled.py
agstoolbox/core/ags/script_module.py
agstoolbox/core/ags/validate_ags_editor.py
agstoolbox/core/cmdline/__init__.py
agstoolbox/core/cmdline/cmdline.py
agstoolbox/core/cmdline/cmdline_download.py
agstoolbox/core/cmdline/progress.py
agstoolbox/core/gh/__init__.py
agstoolbox/core/gh/agstoolbox_release.py
agstoolbox/core/gh/agstoolbox_releases.py
agstoolbox/core/gh/agstoolbox_update.py
agstoolbox/core/gh/download_release.py
agstoolbox/core/gh/install_release.py
agstoolbox/core/gh/list_releases.py
agstoolbox/core/gh/release.py
agstoolbox/core/settings/__init__.py
agstoolbox/core/settings/settings.py
agstoolbox/core/settings/settings_data.py
agstoolbox/core/settings/settings_utils.py
agstoolbox/core/utils/__init__.py
agstoolbox/core/utils/archive.py
agstoolbox/core/utils/basics.py
agstoolbox/core/utils/downloader.py
agstoolbox/core/utils/file.py
agstoolbox/core/utils/math.py
agstoolbox/core/utils/open_in_browser.py
agstoolbox/core/utils/pe.py
agstoolbox/core/utils/pyinstaller_hacks.py
agstoolbox/core/utils/run.py
agstoolbox/core/utils/singleton.py
agstoolbox/core/utils/startup.py
agstoolbox/core/utils/systemdirs.py
agstoolbox/core/utils/time.py
agstoolbox-0.6.0.dist-info/licenses/AUTHORS
agstoolbox-0.6.0.dist-info/licenses/COPYING
agstoolbox-0.6.0.dist-info/licenses/LICENSE
agstoolbox-0.6.0.dist-info/METADATA
agstoolbox-0.6.0.dist-info/WHEEL
agstoolbox-0.6.0.dist-info/top_level.txt
agstoolbox-0.6.0.dist-info/RECORD
