Metadata-Version: 2.4
Name: agstoolbox
Version: 0.6.0
Summary: Utility to help manage Adventure Game Studio Projects and Editors.
Home-page: https://github.com/ericoporto/agstoolbox
Download-URL: https://github.com/ericoporto/agstoolbox/tarball/0.6.0
Author: erico
Author-email: eri0onpm@gmail.com
License: MIT
Keywords: AGS Toolbox,Adventure Game Studio,development,ags,Game Development,gamedev
Classifier: Intended Audience :: Developers
Classifier: License :: OSI Approved :: MIT License
Classifier: Programming Language :: Python :: 3.8
Classifier: Programming Language :: Python :: 3.9
Classifier: Programming Language :: Python :: 3.10
Classifier: Programming Language :: Python :: 3.11
Classifier: Programming Language :: Python :: 3 :: Only
Requires-Python: >=3.8
License-File: LICENSE
License-File: COPYING
License-File: AUTHORS
Requires-Dist: pyqt6
Requires-Dist: requests
Requires-Dist: defusedxml
Requires-Dist: platformdirs
Requires-Dist: pefile
Requires-Dist: shtab
Dynamic: author
Dynamic: author-email
Dynamic: classifier
Dynamic: description
Dynamic: download-url
Dynamic: home-page
Dynamic: keywords
Dynamic: license
Dynamic: license-file
Dynamic: requires-dist
Dynamic: requires-python
Dynamic: summary
